securepy/__init__.py
securepy/restrictor.py
securepy/security.py
securepy/stdcapture.py
securepy/timing.py
securepy/config/__init__.py
securepy/config/config.py
tests/__init__.py
tests/test_stdcapture.py
securepy-0.6.1.dist-info/LICENSE
securepy-0.6.1.dist-info/METADATA
securepy-0.6.1.dist-info/WHEEL
securepy-0.6.1.dist-info/top_level.txt
securepy-0.6.1.dist-info/RECORD
