Metadata-Version: 2.1
Name: securepy
Version: 0.6.1
Summary: Secure unknown python code execution
Home-page: https://github.com/ItsDrike/SecurePy
Author: ItsDrike
Author-email: itsdrikeofficial@gmail.com
License: Apache-2.0
Platform: UNKNOWN
Classifier: Development Status :: 4 - Beta
Classifier: License :: OSI Approved :: Apache Software License
Classifier: Programming Language :: Python :: 3
Classifier: Programming Language :: Python :: 3.7
Classifier: Programming Language :: Python :: 3.8
Classifier: Programming Language :: Python :: 3.9
Classifier: Operating System :: OS Independent
Classifier: Operating System :: POSIX
Classifier: Topic :: System
Requires-Python: >=3.7
